odoo/addons/project_version/README.rst
odoo/addons/project_version/__init__.py
odoo/addons/project_version/__manifest__.py
odoo/addons/project_version/i18n/es.po
odoo/addons/project_version/i18n/it.po
odoo/addons/project_version/i18n/project_version.pot
odoo/addons/project_version/models/__init__.py
odoo/addons/project_version/models/project_project.py
odoo/addons/project_version/models/project_task.py
odoo/addons/project_version/models/project_version.py
odoo/addons/project_version/readme/CONTRIBUTORS.md
odoo/addons/project_version/readme/DESCRIPTION.md
odoo/addons/project_version/readme/USAGE.md
odoo/addons/project_version/security/ir.model.access.csv
odoo/addons/project_version/static/description/icon.png
odoo/addons/project_version/static/description/icon.svg
odoo/addons/project_version/static/description/index.html
odoo/addons/project_version/views/project_project_views.xml
odoo/addons/project_version/views/project_task_views.xml
odoo/addons/project_version/views/project_version_views.xml
odoo_addon_project_version-18.0.1.0.0.2.dist-info/METADATA
odoo_addon_project_version-18.0.1.0.0.2.dist-info/WHEEL
odoo_addon_project_version-18.0.1.0.0.2.dist-info/top_level.txt
odoo_addon_project_version-18.0.1.0.0.2.dist-info/RECORD
